{"errors":[],"warnings":["./src/components/Layout.jsx\nThere are multiple modules with names that only differ in casing.\nThis can lead to unexpected behavior when compiling on a filesystem with other case-semantic.\nUse equal casing. Compare these module identifiers:\n* C:\\Users\\ginah\\Desktop\\portfolio\\node_modules\\gatsby\\dist\\utils\\babel-loader.js??ref--4-0!C:\\Users\\ginah\\Desktop\\portfolio\\src\\components\\Layout.jsx\n    Used by 2 module(s), i. e.\n    C:\\Users\\ginah\\Desktop\\portfolio\\node_modules\\gatsby\\dist\\utils\\babel-loader.js??ref--4-0!C:\\Users\\ginah\\Desktop\\portfolio\\src\\templates\\post.js\n* C:\\Users\\ginah\\Desktop\\portfolio\\node_modules\\gatsby\\dist\\utils\\babel-loader.js??ref--4-0!C:\\Users\\ginah\\Desktop\\portfolio\\src\\components\\layout.jsx\n    Used by 10 module(s), i. e.\n    C:\\Users\\ginah\\Desktop\\portfolio\\node_modules\\gatsby\\dist\\utils\\babel-loader.js??ref--4-0!C:\\Users\\ginah\\Desktop\\portfolio\\src\\pages\\project.js"],"namedChunkGroups":{"polyfill":{"chunks":[1,10],"assets":["webpack-runtime-1a678d3e332f2c84474a.js","webpack-runtime-1a678d3e332f2c84474a.js.map","polyfill-dee37dcd29fe05bc0cef.js","polyfill-dee37dcd29fe05bc0cef.js.map"],"children":{},"childAssets":{}},"app":{"chunks":[1,9,11,2],"assets":["webpack-runtime-1a678d3e332f2c84474a.js","webpack-runtime-1a678d3e332f2c84474a.js.map","framework-b5b229d58c3c710d5429.js","framework-b5b229d58c3c710d5429.js.map","styles.72aaaf0e0ee13537468c.css","styles-24c541b6ac347bae38f1.js","styles-24c541b6ac347bae38f1.js.map","app-b58ceee5731458a1bcd6.js","app-b58ceee5731458a1bcd6.js.map"],"children":{},"childAssets":{}},"component---src-pages-404-js":{"chunks":[0,3],"assets":["commons-8ac427d6be71286acd56.js","commons-8ac427d6be71286acd56.js.map","component---src-pages-404-js-1cab9dbccc9cd001de94.js","component---src-pages-404-js-1cab9dbccc9cd001de94.js.map"],"children":{},"childAssets":{}},"component---src-pages-about-js":{"chunks":[0,4],"assets":["commons-8ac427d6be71286acd56.js","commons-8ac427d6be71286acd56.js.map","component---src-pages-about-js-d0c80a2a26a94b099ee2.js","component---src-pages-about-js-d0c80a2a26a94b099ee2.js.map"],"children":{},"childAssets":{}},"component---src-pages-cv-js":{"chunks":[0,5],"assets":["commons-8ac427d6be71286acd56.js","commons-8ac427d6be71286acd56.js.map","component---src-pages-cv-js-dda5d00cd8b6502c95b7.js","component---src-pages-cv-js-dda5d00cd8b6502c95b7.js.map"],"children":{},"childAssets":{}},"component---src-pages-index-js":{"chunks":[0,6],"assets":["commons-8ac427d6be71286acd56.js","commons-8ac427d6be71286acd56.js.map","component---src-pages-index-js-3ecebcb1df18a117bb75.js","component---src-pages-index-js-3ecebcb1df18a117bb75.js.map"],"children":{},"childAssets":{}},"component---src-pages-project-js":{"chunks":[0,7],"assets":["commons-8ac427d6be71286acd56.js","commons-8ac427d6be71286acd56.js.map","component---src-pages-project-js-c9c0c27c112b987c0d6d.js","component---src-pages-project-js-c9c0c27c112b987c0d6d.js.map"],"children":{},"childAssets":{}},"component---src-templates-post-js":{"chunks":[0,8],"assets":["commons-8ac427d6be71286acd56.js","commons-8ac427d6be71286acd56.js.map","component---src-templates-post-js-3cb268a6fc8487e383a0.js","component---src-templates-post-js-3cb268a6fc8487e383a0.js.map"],"children":{},"childAssets":{}}},"assetsByChunkName":{"polyfill":["webpack-runtime-1a678d3e332f2c84474a.js","polyfill-dee37dcd29fe05bc0cef.js"],"app":["webpack-runtime-1a678d3e332f2c84474a.js","framework-b5b229d58c3c710d5429.js","styles.72aaaf0e0ee13537468c.css","styles-24c541b6ac347bae38f1.js","app-b58ceee5731458a1bcd6.js"],"component---src-pages-404-js":["commons-8ac427d6be71286acd56.js","component---src-pages-404-js-1cab9dbccc9cd001de94.js"],"component---src-pages-about-js":["commons-8ac427d6be71286acd56.js","component---src-pages-about-js-d0c80a2a26a94b099ee2.js"],"component---src-pages-cv-js":["commons-8ac427d6be71286acd56.js","component---src-pages-cv-js-dda5d00cd8b6502c95b7.js"],"component---src-pages-index-js":["commons-8ac427d6be71286acd56.js","component---src-pages-index-js-3ecebcb1df18a117bb75.js"],"component---src-pages-project-js":["commons-8ac427d6be71286acd56.js","component---src-pages-project-js-c9c0c27c112b987c0d6d.js"],"component---src-templates-post-js":["commons-8ac427d6be71286acd56.js","component---src-templates-post-js-3cb268a6fc8487e383a0.js"]}}